crawlio/__init__.py
crawlio/classes.py
crawlio/cli.py
crawlio/cmd.py
crawlio/crawlio.py
crawlio/web/__init__.py
crawlio/web/app.py
crawlio-2.3.3.dist-info/COPYING
crawlio-2.3.3.dist-info/METADATA
crawlio-2.3.3.dist-info/WHEEL
crawlio-2.3.3.dist-info/entry_points.txt
crawlio-2.3.3.dist-info/top_level.txt
crawlio-2.3.3.dist-info/RECORD
