Metadata-Version: 2.1
Name: crawlio
Version: 2.3.3
Summary: Simple and customizable web crawler built with Python's asyncio
Home-page: https://github.com/maximiliancw/crawlio
Author: Maximilian Wolf
Author-email: maximilian.wolf@innovinati.com
License: UNKNOWN
Platform: UNKNOWN
Classifier: Development Status :: 4 - Beta
Classifier: License :: OSI Approved :: GNU General Public License v3 (GPLv3)
Classifier: Natural Language :: English
Classifier: Operating System :: OS Independent
Classifier: Programming Language :: Python :: 3.6
Classifier: Programming Language :: Python :: 3.7
Classifier: Programming Language :: Python :: 3.8
Classifier: Programming Language :: Python :: Implementation :: CPython
Classifier: Programming Language :: Python :: Implementation :: PyPy
Classifier: Framework :: AsyncIO
License-File: COPYING
Requires-Dist: aiohttp
Requires-Dist: click
Requires-Dist: fastapi
Requires-Dist: parsel
